pyqtgraph/PlotData.py
pyqtgraph/Point.py
pyqtgraph/SRTTransform.py
pyqtgraph/SRTTransform3D.py
pyqtgraph/SignalProxy.py
pyqtgraph/ThreadsafeTimer.py
pyqtgraph/Transform3D.py
pyqtgraph/Vector.py
pyqtgraph/WidgetGroup.py
pyqtgraph/__init__.py
pyqtgraph/colormap.py
pyqtgraph/configfile.py
pyqtgraph/debug.py
pyqtgraph/exceptionHandling.py
pyqtgraph/frozenSupport.py
pyqtgraph/functions.py
pyqtgraph/functions_numba.py
pyqtgraph/functions_qimage.py
pyqtgraph/reload.py
pyqtgraph/units.py
pyqtgraph/GraphicsScene/GraphicsScene.py
pyqtgraph/GraphicsScene/__init__.py
pyqtgraph/GraphicsScene/exportDialog.py
pyqtgraph/GraphicsScene/exportDialogTemplate_generic.py
pyqtgraph/GraphicsScene/mouseEvents.py
pyqtgraph/Qt/QtSvg.pyi
pyqtgraph/Qt/QtTest.pyi
pyqtgraph/Qt/__init__.py
pyqtgraph/Qt/__init__.pyi
pyqtgraph/Qt/internals.py
pyqtgraph/Qt/QtCore/__init__.py
pyqtgraph/Qt/QtCore/__init__.pyi
pyqtgraph/Qt/QtGui/__init__.py
pyqtgraph/Qt/QtGui/__init__.pyi
pyqtgraph/Qt/QtWidgets/__init__.py
pyqtgraph/Qt/QtWidgets/__init__.pyi
pyqtgraph/Qt/compat/__init__.py
pyqtgraph/canvas/Canvas.py
pyqtgraph/canvas/CanvasItem.py
pyqtgraph/canvas/CanvasManager.py
pyqtgraph/canvas/CanvasTemplate_generic.py
pyqtgraph/canvas/TransformGuiTemplate_generic.py
pyqtgraph/canvas/__init__.py
pyqtgraph/colors/__init__.py
pyqtgraph/colors/palette.py
pyqtgraph/colors/maps/CC-BY license - applies to CET color map data.txt
"pyqtgraph/colors/maps/CC0 legal code - applies to virids, magma, plasma, inferno and cividis.txt"
pyqtgraph/colors/maps/CET-C1.csv
pyqtgraph/colors/maps/CET-C1s.csv
pyqtgraph/colors/maps/CET-C2.csv
pyqtgraph/colors/maps/CET-C2s.csv
pyqtgraph/colors/maps/CET-C3.csv
pyqtgraph/colors/maps/CET-C3s.csv
pyqtgraph/colors/maps/CET-C4.csv
pyqtgraph/colors/maps/CET-C4s.csv
pyqtgraph/colors/maps/CET-C5.csv
pyqtgraph/colors/maps/CET-C5s.csv
pyqtgraph/colors/maps/CET-C6.csv
pyqtgraph/colors/maps/CET-C6s.csv
pyqtgraph/colors/maps/CET-C7.csv
pyqtgraph/colors/maps/CET-C7s.csv
pyqtgraph/colors/maps/CET-CBC1.csv
pyqtgraph-0.13.6.dist-info/LICENSE.txt
pyqtgraph-0.13.6.dist-info/METADATA
pyqtgraph-0.13.6.dist-info/WHEEL
pyqtgraph-0.13.6.dist-info/top_level.txt
pyqtgraph-0.13.6.dist-info/RECORD
